setup.py
centrifuge_postgresql/__init__.py
centrifuge_postgresql.egg-info/PKG-INFO
centrifuge_postgresql.egg-info/SOURCES.txt
centrifuge_postgresql.egg-info/dependency_links.txt
centrifuge_postgresql.egg-info/requires.txt
centrifuge_postgresql.egg-info/top_level.txt