Metadata-Version: 1.0
Name: centrifuge-postgresql
Version: 0.2.0
Summary: PostgreSQL structure backend for Centrifuge
Home-page: https://github.com/centrifugal/centrifuge-postgresql
Author: Alexandr Emelin
Author-email: frvzmb@gmail.com
License: MIT
Download-URL: https://github.com/centrifugal/centrifuge-postgresql
Platform: UNKNOWN
Classifier: Development Status :: 3 - Alpha
Classifier: Programming Language :: Python
Classifier: Programming Language :: Python :: 2.6
Classifier: Programming Language :: Python :: 2.7
Classifier: Programming Language :: Python :: 3.3
Classifier: Environment :: Console
Classifier: Intended Audience :: Developers
Classifier: Intended Audience :: System Administrators
Classifier: License :: OSI Approved :: Apache Software License
Classifier: Topic :: Internet :: WWW/HTTP
Classifier: Topic :: Software Development
Classifier: Topic :: System :: Networking
Classifier: Topic :: Terminals
Classifier: Topic :: Text Processing
Classifier: Topic :: Utilities
